grapheneapi/__init__.py
grapheneapi/exceptions.py
grapheneapi/grapheneapi.py
grapheneapi/grapheneclient.py
grapheneapi/graphenehttprpc.py
grapheneapi/graphenews.py
grapheneapi/graphenewsprotocol.py
grapheneapi/graphenewsrpc.py
graphenebase/__init__.py
graphenebase/account.py
graphenebase/base58.py
graphenebase/bip38.py
graphenebase/chains.py
graphenebase/dictionary.py
graphenebase/ecdsa.py
graphenebase/objects.py
graphenebase/objecttypes.py
graphenebase/operationids.py
graphenebase/operations.py
graphenebase/signedtransactions.py
graphenebase/transactions.py
graphenebase/types.py
onegramlib-1.0.7.dist-info/LICENSE.txt
onegramlib-1.0.7.dist-info/METADATA
onegramlib-1.0.7.dist-info/WHEEL
onegramlib-1.0.7.dist-info/top_level.txt
onegramlib-1.0.7.dist-info/zip-safe
onegramlib-1.0.7.dist-info/RECORD
