Metadata-Version: 2.1
Name: onegramlib
Version: 1.0.7
Summary: Python library for OneGram project graphene-based blockchains
Home-page: https://gitlab.com/onegram-developers/python-onegramlib
Author: 01People
Author-email: info@01people.com
Maintainer: 01People
Maintainer-email: info@01people.com
License: UNKNOWN
Download-URL: https://gitlab.com/onegram-developers/python-onegramlib/-/archive/v1.0.7/python-onegramlib-v1.0.7.zip
Keywords: onegram,api,rpc,ecdsa,secp256k1
Platform: UNKNOWN
Classifier: License :: OSI Approved :: MIT License
Classifier: Operating System :: OS Independent
Classifier: Programming Language :: Python :: 3
Classifier: Development Status :: 3 - Alpha
Classifier: Intended Audience :: Developers
Requires-Dist: ecdsa
Requires-Dist: requests
Requires-Dist: websocket-client
Requires-Dist: pylibscrypt
Requires-Dist: pycryptodome
